dxshll/__init__.py
dxshll-0.0.1.data/scripts/foo.sh
dxshll-0.0.1.dist-info/LICENSE
dxshll-0.0.1.dist-info/METADATA
dxshll-0.0.1.dist-info/WHEEL
dxshll-0.0.1.dist-info/top_level.txt
dxshll-0.0.1.dist-info/RECORD
